MANIFEST.in
Readme.md
dataproviders.txt
dev-requirements.frozen.txt
dev-requirements.txt
licence.txt
noxfile.py
requirements.frozen.txt
requirements.txt
setup.cfg
setup.py
pandas_quant_data_provider/__init__.py
pandas_quant_data_provider/fetch.py
pandas_quant_data_provider/symbol.py
pandas_quant_data_provider.egg-info/PKG-INFO
pandas_quant_data_provider.egg-info/SOURCES.txt
pandas_quant_data_provider.egg-info/dependency_links.txt
pandas_quant_data_provider.egg-info/requires.txt
pandas_quant_data_provider.egg-info/top_level.txt
pandas_quant_data_provider/data_provider/__init__.py
pandas_quant_data_provider/data_provider/time_utils.py
pandas_quant_data_provider/data_provider/yf/__init__.py
pandas_quant_data_provider/data_provider/yf/yfinance_provider.py
scraper/__init__.py
scraper/dolting.py
scraper/fetch_optionable_stocks.py
scraper/fetch_yfinance.py