Metadata-Version: 2.1
Name: pandas-quant-data-provider
Version: 0.2.7
Summary: Augment pandas DataFrame with methods to fetch time series data for quant finance
Home-page: https://github.com/KIC/pandas-ml-quant/pandas-quant-data-provider
Author: KIC
Author-email: 
License: MIT
Keywords: pandas,ml,util,quant
Platform: UNKNOWN
Classifier: Development Status :: 3 - Alpha
Classifier: Intended Audience :: Developers
Classifier: Topic :: Software Development :: Build Tools
Classifier: License :: OSI Approved :: MIT License
Classifier: Programming Language :: Python :: 3
Classifier: Programming Language :: Python :: 3.8
Provides-Extra: dev
